evoml_preprocessor_internal/__init__.py
evoml_preprocessor_internal/__main__.py
evoml_preprocessor_internal/py.typed
evoml_preprocessor_internal/preprocess/__init__.py
evoml_preprocessor_internal/preprocess/preprocessor.py
evoml_preprocessor_internal/setup/.version
evoml_preprocessor_internal/setup/requirements.txt
evoml_preprocessor_internal/setup/requirements_develop.txt
evoml_preprocessor_internal/utils/__init__.py
evoml_preprocessor_internal/utils/io_structure.py
turintech_evoml_preprocessor_internal-5.1.1.dist-info/LICENSE
turintech_evoml_preprocessor_internal-5.1.1.dist-info/METADATA
turintech_evoml_preprocessor_internal-5.1.1.dist-info/WHEEL
turintech_evoml_preprocessor_internal-5.1.1.dist-info/top_level.txt
turintech_evoml_preprocessor_internal-5.1.1.dist-info/RECORD
