Metadata-Version: 2.1
Name: turintech-evoml-preprocessor-internal
Version: 5.1.1
Summary: Preprocess data.
Home-page: https://turintech.ai
Author: Turing Intelligence Technology
License: TURING INTELLIGENCE TECHNOLOGY LIMITED END-USER LICENCE
Keywords: turintech,evoml,preprocessor
Classifier: Development Status :: 5 - Production/Stable
Classifier: License :: Other/Proprietary License
Classifier: Programming Language :: Python :: 3.9
Classifier: Programming Language :: Python :: 3.10
Classifier: Programming Language :: Python :: 3.11
Requires-Python: >=3.9,<4
License-File: LICENSE
Requires-Dist: turintech-evoml-preprocessor[all] (==5.1.1)
